marrow/schema/__init__.py
marrow/schema/declarative.py
marrow/schema/exc.py
marrow/schema/meta.py
marrow/schema/release.py
marrow/schema/testing.py
marrow/schema/util.py
marrow/schema/__pycache__/__init__.cpython-37.opt-1.pyc
marrow/schema/__pycache__/declarative.cpython-37.opt-1.pyc
marrow/schema/__pycache__/exc.cpython-37.opt-1.pyc
marrow/schema/__pycache__/meta.cpython-37.opt-1.pyc
marrow/schema/__pycache__/release.cpython-37.opt-1.pyc
marrow/schema/__pycache__/testing.cpython-37.opt-1.pyc
marrow/schema/__pycache__/util.cpython-37.opt-1.pyc
marrow/schema/transform/__init__.py
marrow/schema/transform/base.py
marrow/schema/transform/complex.py
marrow/schema/transform/container.py
marrow/schema/transform/primitive.py
marrow/schema/transform/type.py
marrow/schema/transform/__pycache__/__init__.cpython-37.opt-1.pyc
marrow/schema/transform/__pycache__/base.cpython-37.opt-1.pyc
marrow/schema/transform/__pycache__/complex.cpython-37.opt-1.pyc
marrow/schema/transform/__pycache__/container.cpython-37.opt-1.pyc
marrow/schema/transform/__pycache__/primitive.cpython-37.opt-1.pyc
marrow/schema/transform/__pycache__/type.cpython-37.opt-1.pyc
marrow/schema/validate/__init__.py
marrow/schema/validate/base.py
marrow/schema/validate/compound.py
marrow/schema/validate/date.py
marrow/schema/validate/geo.py
marrow/schema/validate/network.py
marrow/schema/validate/pattern.py
marrow/schema/validate/util.py
marrow/schema/validate/__pycache__/__init__.cpython-37.opt-1.pyc
marrow/schema/validate/__pycache__/base.cpython-37.opt-1.pyc
marrow/schema/validate/__pycache__/compound.cpython-37.opt-1.pyc
marrow/schema/validate/__pycache__/date.cpython-37.opt-1.pyc
marrow/schema/validate/__pycache__/geo.cpython-37.opt-1.pyc
marrow/schema/validate/__pycache__/network.cpython-37.opt-1.pyc
marrow/schema/validate/__pycache__/pattern.cpython-37.opt-1.pyc
marrow/schema/validate/__pycache__/util.cpython-37.opt-1.pyc
marrow/schema/validation/__init__.py
marrow/schema/validation/base.py
marrow.schema-2.0.0.dist-info/LICENSE.txt
marrow.schema-2.0.0.dist-info/METADATA
marrow.schema-2.0.0.dist-info/WHEEL
marrow.schema-2.0.0.dist-info/top_level.txt
marrow.schema-2.0.0.dist-info/RECORD
