Metadata-Version: 2.1
Name: marrow.schema
Version: 2.0.0
Summary: A generic declarative syntax toolkit for Python objects that uses itself to define itself.  Really.
Home-page: https://github.com/marrow/schema/
Author: Alice Bevan-McGregor
Author-email: alice@gothcandy.com
License: MIT
Keywords: declarative syntax,metaprogramming,schema toolkit
Platform: UNKNOWN
Classifier: Development Status :: 5 - Production/Stable
Classifier: Intended Audience :: Developers
Classifier: License :: OSI Approved :: MIT License
Classifier: Operating System :: OS Independent
Classifier: Programming Language :: Python
Classifier: Programming Language :: Python :: 3
Classifier: Programming Language :: Python :: 3.3
Classifier: Programming Language :: Python :: 3.4
Classifier: Programming Language :: Python :: 3.5
Classifier: Programming Language :: Python :: 3.6
Classifier: Programming Language :: Python :: 3.7
Classifier: Programming Language :: Python :: Implementation :: CPython
Classifier: Programming Language :: Python :: Implementation :: PyPy
Classifier: Topic :: Software Development :: Libraries :: Python Modules
Classifier: Topic :: Utilities
Provides-Extra: development
Requires-Dist: pytest ; extra == 'development'
Requires-Dist: pytest-cov ; extra == 'development'
Requires-Dist: pytest-spec ; extra == 'development'
Requires-Dist: pytest-flakes ; extra == 'development'
